cloudtoken_plugin/__init__.py
cloudtoken_plugin/google_auth.py
cloudtoken_plugin/google_aws.py
cloudtoken_plugin.google_aws-0.1.764.dist-info/LICENSE.txt
cloudtoken_plugin.google_aws-0.1.764.dist-info/METADATA
cloudtoken_plugin.google_aws-0.1.764.dist-info/WHEEL
cloudtoken_plugin.google_aws-0.1.764.dist-info/top_level.txt
cloudtoken_plugin.google_aws-0.1.764.dist-info/RECORD
