Metadata-Version: 2.1
Name: cloudtoken-plugin.google-aws
Version: 0.1.764
Summary: Google AWS plugin for cloudtoken.
Home-page: https://bitbucket.org/atlassian/cloudtoken
Author: Atlassian Cloud Engineering
Author-email: cloud-team@atlassian.com
License: Apache
Platform: UNKNOWN
Requires-Python: >=3.5
Requires-Dist: cloudtoken (>=0.1.12)
Requires-Dist: python-u2flib-host
Requires-Dist: beautifulsoup4
Requires-Dist: boto3
Requires-Dist: Pillow
Requires-Dist: requests
Requires-Dist: six
